verilog/coincidence_detector.v
`timescale 1ns/1ps
module coincidence_detector(a,b,c,d,SPAD_valid);
input a,b,c,d;
output SPAD_valid;
wire [8:0] w;

nand(w[0],a,b);
nand(w[1],c,d);
nand(w[2],a,c);
nand(w[3],a,d);
nand(w[4],c,b);
nand(w[5],d,b);
nand(w[6],w[0],w[1]);
nand(w[7],w[2],w[3]);
nand(w[8],w[4],w[5]);
or(SPAD_valid,w[6],w[7],w[8]);

endmodule

verilog/tb_coincidence_detector.v
`timescale 1ns/1ps
module coincidence_test;
  reg a,b,c,d;
  initial begin
   $dumpfile("coincidence_test.vcd");
   $dumpvars(0,coincidence_test);
   a=0;
   b=0;
   c=0;
   d=0;
   #5 a = 1;
   #5 b = 1;
   #5 c = 1;
      a = 0;
   #6 d = 1;
   #1 c = 0;
   #2 b = 0;
   #1 a = 1;
  end
  wire out;
  coincidence_detector d1 (a,b,c,d,out);
endmodule

verilog/coincidence_test.vcd
$date
	Fri Sep 18 22:58:44 2020
$end
$version
	Icarus Verilog
$end
$timescale
	1ps
$end
$scope module coincidence_test $end
$var wire 1 ! out $end
$var reg 1 " a $end
$var reg 1 # b $end
$var reg 1 $ c $end
$var reg 1 % d $end
$scope module d1 $end
$var wire 1 ! SPAD_valid $end
$var wire 1 " a $end
$var wire 1 # b $end
$var wire 1 $ c $end
$var wire 1 % d $end
$var wire 9 & w [8:0] $end
$upscope $end
$upscope $end
$enddefinitions $end
#0
$dumpvars
b111111 &
0%
0$
0#
0"
0!
$end
#5000
1"
#10000
1!
b1111110 &
1#
#15000
b100101111 &
0"
1$
#21000
b101001101 &
1%
#22000
b100011111 &
0$
#24000
0!
b111111 &
0#
#25000
1!
b10110111 &
1"
